Metadata-Version: 2.2
Name: icm20602
Version: 0.2.2
Summary: A Python library for ICM20602 sensor, Raspberry PI ready
Home-page: https://github.com/kagankongar/ICM20602
Author: Kagan Kongare
Author-email: kagan.kongar@gmail.com
Classifier: Programming Language :: Python :: 3
Classifier: License :: OSI Approved :: MIT License
Classifier: Operating System :: OS Independent
Requires-Python: >=3.6
License-File: LICENSE
Requires-Dist: spidev
Dynamic: author
Dynamic: author-email
Dynamic: classifier
Dynamic: description
Dynamic: description-content-type
Dynamic: home-page
Dynamic: requires-dist
Dynamic: requires-python
Dynamic: summary
